google_adk_arcade/__init__.py
google_adk_arcade/_utils.py
google_adk_arcade/errors.py
google_adk_arcade/tools.py
google_adk_arcade-0.0.2.dist-info/METADATA
google_adk_arcade-0.0.2.dist-info/WHEEL
google_adk_arcade-0.0.2.dist-info/licenses/LICENSE
google_adk_arcade-0.0.2.dist-info/RECORD
